MANIFEST.in
README.md
setup.cfg
setup.py
pyramid_straw/__init__.py
pyramid_straw.egg-info/PKG-INFO
pyramid_straw.egg-info/SOURCES.txt
pyramid_straw.egg-info/dependency_links.txt
pyramid_straw.egg-info/requires.txt
pyramid_straw.egg-info/top_level.txt
pyramid_straw/panel/__init__.py
pyramid_straw/panel/debugpanel_wsgi_app/__init__.py
pyramid_straw/panel/debugpanel_wsgi_app/views.py
pyramid_straw/panel/debugpanel_wsgi_app/static/pev/bootstrap.js
pyramid_straw/panel/debugpanel_wsgi_app/static/pev/enums.js
pyramid_straw/panel/debugpanel_wsgi_app/static/pev/index.html
pyramid_straw/panel/debugpanel_wsgi_app/static/pev/pipes.js
pyramid_straw/panel/debugpanel_wsgi_app/static/pev/assets/img/pev-logo.png
pyramid_straw/panel/debugpanel_wsgi_app/static/pev/assets/js/Reflect.js
pyramid_straw/panel/debugpanel_wsgi_app/static/pev/assets/js/Rx.min.js
pyramid_straw/panel/debugpanel_wsgi_app/static/pev/assets/js/angular2-polyfills.js
pyramid_straw/panel/debugpanel_wsgi_app/static/pev/assets/js/angular2.min.js
pyramid_straw/panel/debugpanel_wsgi_app/static/pev/assets/js/es6-shim.min.js
pyramid_straw/panel/debugpanel_wsgi_app/static/pev/assets/js/highlight.js
pyramid_straw/panel/debugpanel_wsgi_app/static/pev/assets/js/http.min.js
pyramid_straw/panel/debugpanel_wsgi_app/static/pev/assets/js/index.js
pyramid_straw/panel/debugpanel_wsgi_app/static/pev/assets/js/moment.js
pyramid_straw/panel/debugpanel_wsgi_app/static/pev/assets/js/router.js
pyramid_straw/panel/debugpanel_wsgi_app/static/pev/assets/js/system.src.js
pyramid_straw/panel/debugpanel_wsgi_app/static/pev/bundles/app.js
pyramid_straw/panel/debugpanel_wsgi_app/static/pev/components/about/about.js
pyramid_straw/panel/debugpanel_wsgi_app/static/pev/components/app/app.js
pyramid_straw/panel/debugpanel_wsgi_app/static/pev/components/plan-list/plan-list.js
pyramid_straw/panel/debugpanel_wsgi_app/static/pev/components/plan-new/plan-new.js
pyramid_straw/panel/debugpanel_wsgi_app/static/pev/components/plan-node/plan-node.js
pyramid_straw/panel/debugpanel_wsgi_app/static/pev/components/plan-view/plan-view.js
pyramid_straw/panel/debugpanel_wsgi_app/static/pev/css/styles.css
